[{"iconClass":"fa-folder","objectID":"https://woodwen.github.io/categories/android","title":"Android","type":"category","url":"https://woodwen.github.io/categories/android"},{"iconClass":"fa-folder","objectID":"https://woodwen.github.io/categories/build","title":"Build","type":"category","url":"https://woodwen.github.io/categories/build"},{"iconClass":"fa-folder","objectID":"https://woodwen.github.io/categories/flutter","title":"Flutter","type":"category","url":"https://woodwen.github.io/categories/flutter"},{"iconClass":"fa-folder","objectID":"https://woodwen.github.io/categories/jellyfin","title":"Jellyfin","type":"category","url":"https://woodwen.github.io/categories/jellyfin"},{"iconClass":"fa-folder","objectID":"https://woodwen.github.io/categories/%E6%B2%B9%E7%8C%B4","title":"油猴","type":"category","url":"https://woodwen.github.io/categories/%E6%B2%B9%E7%8C%B4"},{"iconClass":"fa-folder","objectID":"https://woodwen.github.io/categories/%E9%9A%8F%E7%AC%94","title":"随笔","type":"category","url":"https://woodwen.github.io/categories/%E9%9A%8F%E7%AC%94"},{"iconClass":"fa-user","objectID":"https://woodwen.github.io/author/woodwen","title":"woodwen","type":"author","url":"https://woodwen.github.io/author/woodwen"},{"iconClass":"fa-tag","objectID":"https://woodwen.github.io/tags/android","title":"Android","type":"tag","url":"https://woodwen.github.io/tags/android"},{"iconClass":"fa-tag","objectID":"https://woodwen.github.io/tags/blog","title":"Blog","type":"tag","url":"https://woodwen.github.io/tags/blog"},{"iconClass":"fa-tag","objectID":"https://woodwen.github.io/tags/build","title":"Build","type":"tag","url":"https://woodwen.github.io/tags/build"},{"iconClass":"fa-tag","objectID":"https://woodwen.github.io/tags/dart","title":"Dart","type":"tag","url":"https://woodwen.github.io/tags/dart"},{"iconClass":"fa-tag","objectID":"https://woodwen.github.io/tags/docker","title":"Docker","type":"tag","url":"https://woodwen.github.io/tags/docker"},{"iconClass":"fa-tag","objectID":"https://woodwen.github.io/tags/docker-compose","title":"Docker compose","type":"tag","url":"https://woodwen.github.io/tags/docker-compose"},{"iconClass":"fa-tag","objectID":"https://woodwen.github.io/tags/flutter","title":"Flutter","type":"tag","url":"https://woodwen.github.io/tags/flutter"},{"iconClass":"fa-tag","objectID":"https://woodwen.github.io/tags/fvm","title":"Fvm","type":"tag","url":"https://woodwen.github.io/tags/fvm"},{"iconClass":"fa-tag","objectID":"https://woodwen.github.io/tags/github","title":"Github","type":"tag","url":"https://woodwen.github.io/tags/github"},{"iconClass":"fa-tag","objectID":"https://woodwen.github.io/tags/github-pages","title":"Github pages","type":"tag","url":"https://woodwen.github.io/tags/github-pages"},{"iconClass":"fa-tag","objectID":"https://woodwen.github.io/tags/hugo","title":"Hugo","type":"tag","url":"https://woodwen.github.io/tags/hugo"},{"iconClass":"fa-tag","objectID":"https://woodwen.github.io/tags/jellyfin","title":"Jellyfin","type":"tag","url":"https://woodwen.github.io/tags/jellyfin"},{"iconClass":"fa-tag","objectID":"https://woodwen.github.io/tags/js","title":"Js","type":"tag","url":"https://woodwen.github.io/tags/js"},{"iconClass":"fa-tag","objectID":"https://woodwen.github.io/tags/kotlin","title":"Kotlin","type":"tag","url":"https://woodwen.github.io/tags/kotlin"},{"iconClass":"fa-tag","objectID":"https://woodwen.github.io/tags/mvvm","title":"Mvvm","type":"tag","url":"https://woodwen.github.io/tags/mvvm"},{"iconClass":"fa-tag","objectID":"https://woodwen.github.io/tags/nextcloud","title":"Nextcloud","type":"tag","url":"https://woodwen.github.io/tags/nextcloud"},{"iconClass":"fa-tag","objectID":"https://woodwen.github.io/tags/nginx","title":"Nginx","type":"tag","url":"https://woodwen.github.io/tags/nginx"},{"iconClass":"fa-tag","objectID":"https://woodwen.github.io/tags/onlyoffice","title":"Onlyoffice","type":"tag","url":"https://woodwen.github.io/tags/onlyoffice"},{"iconClass":"fa-tag","objectID":"https://woodwen.github.io/tags/organizr","title":"Organizr","type":"tag","url":"https://woodwen.github.io/tags/organizr"},{"iconClass":"fa-tag","objectID":"https://woodwen.github.io/tags/picgo","title":"Picgo","type":"tag","url":"https://woodwen.github.io/tags/picgo"},{"iconClass":"fa-tag","objectID":"https://woodwen.github.io/tags/picture","title":"Picture","type":"tag","url":"https://woodwen.github.io/tags/picture"},{"iconClass":"fa-tag","objectID":"https://woodwen.github.io/tags/plugin","title":"Plugin","type":"tag","url":"https://woodwen.github.io/tags/plugin"},{"iconClass":"fa-tag","objectID":"https://woodwen.github.io/tags/postgres","title":"Postgres","type":"tag","url":"https://woodwen.github.io/tags/postgres"},{"iconClass":"fa-tag","objectID":"https://woodwen.github.io/tags/reader","title":"Reader","type":"tag","url":"https://woodwen.github.io/tags/reader"},{"iconClass":"fa-tag","objectID":"https://woodwen.github.io/tags/ssl","title":"Ssl","type":"tag","url":"https://woodwen.github.io/tags/ssl"},{"iconClass":"fa-tag","objectID":"https://woodwen.github.io/tags/suibi","title":"Suibi","type":"tag","url":"https://woodwen.github.io/tags/suibi"},{"iconClass":"fa-tag","objectID":"https://woodwen.github.io/tags/ubuntu","title":"Ubuntu","type":"tag","url":"https://woodwen.github.io/tags/ubuntu"},{"iconClass":"fa-tag","objectID":"https://woodwen.github.io/tags/vscode","title":"Vscode","type":"tag","url":"https://woodwen.github.io/tags/vscode"},{"iconClass":"fa-tag","objectID":"https://woodwen.github.io/tags/youhou","title":"Youhou","type":"tag","url":"https://woodwen.github.io/tags/youhou"},{"author":"woodwen","categories":["随笔"],"iconClass":"fa-pencil-alt","language":"en","objectID":"305de1597f6ca5e469d739c43ebdd7fb","tags":["suibi"],"title":"建立真诚的人际关系：远离情感PUA","type":"article","url":"https://woodwen.github.io/article/jianlizhenchengderenjiguanxi-suibi/"},{"author":"woodwen","categories":["随笔"],"iconClass":"fa-pencil-alt","language":"en","objectID":"08eb8eb9e7cfee725473cded3e202177","tags":["suibi"],"title":"低质量的努力：价值与反思","type":"article","url":"https://woodwen.github.io/article/dizhiliangdenuli-suibi/"},{"author":"woodwen","categories":["油猴"],"iconClass":"fa-code","language":"en","objectID":"57c2a3e5b5e593ec20d4614f92d4a42d","tags":["youhou","js"],"title":"油猴入门","type":"code","url":"https://woodwen.github.io/code/youhou-js/"},{"author":"woodwen","categories":["build"],"iconClass":"fa-code","language":"en","objectID":"990797fdbda83087a05f90fba6403404","tags":["build","docker","organizr"],"title":"玩转云桌面（organizr）","type":"code","url":"https://woodwen.github.io/code/build-docker-organizr/"},{"author":"woodwen","categories":["flutter"],"iconClass":"fa-code","language":"en","objectID":"ad010b33b3c564b886751c1652d4f034","tags":["flutter","fvm"],"title":"Flutter fvm","type":"code","url":"https://woodwen.github.io/code/flutter-fvm/"},{"author":"woodwen","categories":["build"],"iconClass":"fa-code","language":"en","objectID":"d9deadd37e2b2c291b46c18d014b7e0b","tags":["build","github","picture","vscode","picgo"],"title":"Github搭建图床","type":"code","url":"https://woodwen.github.io/code/build-github-vscode-picgo/"},{"author":"woodwen","categories":["flutter"],"iconClass":"fa-code","language":"en","objectID":"436ada8a10eead05c8555d3ca214194d","tags":["flutter","dart","plugin"],"title":"Flutter 常用插件","type":"code","url":"https://woodwen.github.io/code/flutter-plugin/"},{"author":"woodwen","categories":["jellyfin"],"iconClass":"fa-code","language":"en","objectID":"764151a13e1a9e618be065157eaf3e25","tags":["ubuntu","docker","jellyfin"],"title":"ubuntu下docker安装jellyfin","type":"code","url":"https://woodwen.github.io/code/build-ubuntu-docker-jellyfin/"},{"author":"woodwen","categories":["build"],"iconClass":"fa-code","language":"en","objectID":"c734cb5f3f657febd935f343cebe055f","tags":["build","docker","docker-compose","nextcloud","onlyoffice","postgres","nginx","ssl"],"title":"使用docker-compose部署Nextcloud和Onlyoffice组合包(包含nginx+ssl+postgres+redis)","type":"code","url":"https://woodwen.github.io/code/build-docker-nextcloud-onlyoffice-postgres-nginx/"},{"author":"woodwen","categories":["build"],"iconClass":"fa-code","language":"en","objectID":"bfc82cf4a6a3b397e31e7a67efeae3cc","tags":["build","hugo","github pages","blog"],"title":"使用Hugo+GithubPages搭建博客","type":"code","url":"https://woodwen.github.io/code/build-hugo-githubpages-blog/"},{"author":"woodwen","categories":["android"],"iconClass":"fa-code","language":"en","objectID":"ed002bd9ea2372499e9063763e156a41","tags":["android","kotlin","mvvm","reader"],"title":"安卓阅读器（Reader）单项目版版","type":"code","url":"https://woodwen.github.io/code/android-reader-single/"},{"author":null,"categories":null,"iconClass":"fa-pencil-alt","language":"en","objectID":"4a8d5afeb7bf789155a16d8e97a68ae8","tags":null,"title":"Archive Page","type":"archive","url":"https://woodwen.github.io/archive/"}]